py_lua_vm-0.1.0.dist-info/licenses/LICENSE
pylua_vm/__init__.py
pylua_vm/exceptions.py
pylua_vm/lua_process.py
pylua_vm/networking.py
pylua_vm/vm_manager.py
py_lua_vm-0.1.0.dist-info/METADATA
py_lua_vm-0.1.0.dist-info/WHEEL
py_lua_vm-0.1.0.dist-info/top_level.txt
py_lua_vm-0.1.0.dist-info/RECORD
