Metadata-Version: 2.4
Name: py-lua-vm
Version: 0.1.0
Summary: Process-isolated networked Lua VMs managed from Python
Requires-Python: >=3.7
License-File: LICENSE
Dynamic: license-file
